{
  "constraints": [
    {
      "cells": [
        [
          0,
          0
        ],
        [
          0,
          1
        ]
      ],
      "relationValue": "=",
      "type": "relation"
    },
    {
      "cells": [
        [
          2,
          1
        ],
        [
          2,
          2
        ]
      ],
      "relationValue": "=",
      "type": "relation"
    },
    {
      "cells": [
        [
          3,
          2
        ],
        [
          4,
          2
        ]
      ],
      "relationValue": "x",
      "type": "relation"
    },
    {
      "cells": [
        [
          3,
          4
        ],
        [
          4,
          4
        ]
      ],
      "relationValue": "x",
      "type": "relation"
    },
    {
      "cells": [
        [
          4,
          1
        ],
        [
          4,
          2
        ]
      ],
      "relationValue": "=",
      "type": "relation"
    },
    {
      "cells": [
        [
          5,
          1
        ],
        [
          5,
          2
        ]
      ],
      "relationValue": "x",
      "type": "relation"
    },
    {
      "cells": [
        [
          5,
          2
        ],
        [
          5,
          3
        ]
      ],
      "relationValue": "=",
      "type": "relation"
    }
  ],
  "givens": [
    [
      0,
      5
    ],
    [
      1,
      2
    ],
    [
      2,
      3
    ],
    [
      4,
      1
    ],
    [
      4,
      5
    ],
    [
      5,
      0
    ],
    [
      5,
      3
    ],
    [
      5,
      4
    ],
    [
      5,
      5
    ]
  ],
  "grid": [
    [
      null,
      null,
      null,
      null,
      null,
      "S"
    ],
    [
      null,
      null,
      "M",
      null,
      null,
      null
    ],
    [
      null,
      null,
      null,
      "M",
      null,
      null
    ],
    [
      null,
      null,
      null,
      null,
      null,
      null
    ],
    [
      null,
      "M",
      null,
      null,
      null,
      "S"
    ],
    [
      "S",
      null,
      null,
      "M",
      "S",
      "M"
    ]
  ]
}